CHANGELOG.rst
MANIFEST.in
README.rst
setup.py
cos2/__init__.py
cos2/api.py
cos2/auth.py
cos2/compat.py
cos2/defaults.py
cos2/exceptions.py
cos2/http.py
cos2/iterators.py
cos2/json_utils.py
cos2/models.py
cos2/utils.py
cos2.egg-info/PKG-INFO
cos2.egg-info/SOURCES.txt
cos2.egg-info/dependency_links.txt
cos2.egg-info/requires.txt
cos2.egg-info/top_level.txt
examples/data_prepare.py
examples/welcome.py
tests/common.py
tests/test_api_base.py
tests/test_bucket.py
tests/test_chinese.py
tests/test_clean.py
tests/test_iterator.py
tests/test_multipart.py
tests/test_object.py
tests/test_utils.py